odoo/addons/mrp_bom_select_product_variant/README.rst
odoo/addons/mrp_bom_select_product_variant/__init__.py
odoo/addons/mrp_bom_select_product_variant/__manifest__.py
odoo/addons/mrp_bom_select_product_variant/i18n/fr.po
odoo/addons/mrp_bom_select_product_variant/i18n/it.po
odoo/addons/mrp_bom_select_product_variant/i18n/mrp_bom_select_product_variant.pot
odoo/addons/mrp_bom_select_product_variant/model/__init__.py
odoo/addons/mrp_bom_select_product_variant/model/mrp_bom.py
odoo/addons/mrp_bom_select_product_variant/readme/CONTRIBUTORS.rst
odoo/addons/mrp_bom_select_product_variant/readme/DESCRIPTION.rst
odoo/addons/mrp_bom_select_product_variant/static/description/icon.png
odoo/addons/mrp_bom_select_product_variant/static/description/index.html
odoo/addons/mrp_bom_select_product_variant/static/description/mrp_bom_select_product_variant.gif
odoo/addons/mrp_bom_select_product_variant/tests/__init__.py
odoo/addons/mrp_bom_select_product_variant/tests/test_bom_product_variant.py
odoo/addons/mrp_bom_select_product_variant/view/mrp_bom.xml
odoo_addon_mrp_bom_select_product_variant-16.0.1.0.0.4.dist-info/METADATA
odoo_addon_mrp_bom_select_product_variant-16.0.1.0.0.4.dist-info/WHEEL
odoo_addon_mrp_bom_select_product_variant-16.0.1.0.0.4.dist-info/top_level.txt
odoo_addon_mrp_bom_select_product_variant-16.0.1.0.0.4.dist-info/RECORD
